main.py
setup.py
MVDream.egg-info/PKG-INFO
MVDream.egg-info/SOURCES.txt
MVDream.egg-info/dependency_links.txt
MVDream.egg-info/requires.txt
MVDream.egg-info/top_level.txt